{"claims":[{"subject":"Marcus Lee","subject_type":"person","predicate":"self-assessed technical question answer rate","evidence":"i can answer maybe sixty percent of them. for the other forty i need an actual engineer or a pm","object_value":"60%","as_of":"2026-04-08","confidence":0.425,"hypothetical":false},{"subject":"Marcus Lee","subject_type":"person","predicate":"engineer pre-sales response time (current)","evidence":"now it's a week or it doesn't happen","object_value":"a week or it doesn't happen","as_of":"2026-04-08","confidence":0.9,"hypothetical":false},{"subject":"Marcus Lee","subject_type":"person","predicate":"engineer pre-sales response time (at joining)","evidence":"when i first joined an engineer would jump on within twenty four hours","object_value":"within twenty four hours","as_of":"2026-04-08","confidence":0.85,"hypothetical":false},{"subject":"Marcus Lee","subject_type":"person","predicate":"tenure","evidence":"eighteen months. i came from a competitor actually","object_value":"eighteen months","as_of":"2026-04-08","confidence":0.95,"hypothetical":false},{"subject":"Marcus Lee","subject_type":"person","predicate":"prior employer tenure","evidence":"was an ae there for three years","object_value":"three years","as_of":"2026-04-08","confidence":0.9,"hypothetical":false},{"subject":"Marcus Lee","subject_type":"person","predicate":"deal close value (example)","evidence":"for a one point four million dollar customer that's not enough","object_value":"USD 1.4 million","as_of":"2026-04-08","confidence":0.4,"hypothetical":false},{"subject":"multi-property reporting","subject_type":"product","predicate":"identified blocker","evidence":"fix multi-property reporting. seriously. it's the single biggest revenue blocker on enterprise","object_value":"single biggest revenue blocker on enterprise","as_of":"2026-04-08","confidence":0.95,"hypothetical":false},{"subject":"Project Confluence","subject_type":"other","predicate":"current engineering focus","evidence":"everyone in eng is heads down on confluence and the pms are stretched","object_value":"all engineering heads-down (as of interview)","as_of":"2026-04-08","confidence":0.425,"hypothetical":false},{"subject":"Marcus Lee","subject_type":"person","predicate":"self-assessed technical question gap rate","evidence":"for the other forty i need an actual engineer or a pm","object_value":"40%","as_of":"2026-04-08","confidence":0.475,"hypothetical":false},{"subject":"Marcus Lee","subject_type":"person","predicate":"HubSpot prior experience","evidence":"i used hubspot at my last two companies so i was already comfortable with it","object_value":"used at prior two companies","as_of":"2026-04-08","confidence":0.485,"hypothetical":false},{"subject":"Marcus Lee","subject_type":"person","predicate":"HubSpot satisfaction","evidence":"fine. honestly fine. no major complaints from me on the tool itself.","object_value":"no major complaints","as_of":"2026-04-08","confidence":0.95,"hypothetical":false},{"subject":"SMB reps","subject_type":"other","predicate":"HubSpot adoption difficulty","evidence":"some of the smb reps are struggling","object_value":"struggling with HubSpot","as_of":"2026-04-08","confidence":0.45,"hypothetical":false},{"subject":"post-close handoff process","subject_type":"other","predicate":"current artifact quality","evidence":"the artifacts are thin, i'm essentially writing a long slack message about each deal i closed and tom's team is reading that","object_value":"thin artifacts; long Slack message per deal","as_of":"2026-04-08","confidence":0.485,"hypothetical":false},{"subject":"post-close handoff process","subject_type":"other","predicate":"desired state","evidence":"i want a proper structured handoff","object_value":"proper structured handoff","as_of":"2026-04-08","confidence":0.95,"hypothetical":false},{"subject":"Marcus Lee","subject_type":"person","predicate":"reason for joining HelixPay","evidence":"joined helixpay because the product was better on the core payments side and the brazil expansion looked interesting from a career angle","object_value":"better core payments product and Brazil expansion opportunity","as_of":"2026-04-08","confidence":0.485,"hypothetical":false},{"subject":"Marcus Lee","subject_type":"person","predicate":"prior employer role","evidence":"i came from a competitor actually, was an ae there for three years","object_value":"Account Executive","as_of":"2026-04-08","confidence":0.475,"hypothetical":false},{"subject":"Marcus Lee","subject_type":"person","predicate":"prior employer type","evidence":"i came from a competitor actually","object_value":"competitor company","as_of":"2026-04-08","confidence":0.475,"hypothetical":false},{"subject":"PMs at HelixPay","subject_type":"other","predicate":"current capacity status","evidence":"the pms are stretched","object_value":"stretched","as_of":"2026-04-08","confidence":0.92,"hypothetical":false}],"relations":[{"from_entity":"Marcus Lee","to_entity":"HelixPay","link_type":"member_of","raw_verb":null,"as_of":"2026-04-08","confidence":0.99},{"from_entity":"Marcus Lee","to_entity":"Tom","link_type":"mentions","raw_verb":null,"as_of":"2026-04-08","confidence":0.9},{"from_entity":"Marcus Lee","to_entity":"HubSpot","link_type":"mentions","raw_verb":"uses_tool","as_of":"2026-04-08","confidence":0.97},{"from_entity":"CS team","to_entity":"Tom","link_type":"dotted_line_to","raw_verb":null,"as_of":"2026-04-08","confidence":0.9},{"from_entity":"Marcus Lee","to_entity":"competitor company","link_type":"mentions","raw_verb":"former_member_of","as_of":"2026-04-08","confidence":0.93}]}